{
  "source": "assunto_secretaria_secretaria_municipal_de_administração.md",
  "title": "Demandas Colab: Secretaria Municipal de Administração",
  "content": "# Assuntos e Demandas do Aplicativo Colab: Secretaria Municipal de Administração\\n\\nA **Secretaria Municipal de Administração** é o órgão responsável por responder, fiscalizar e solucionar as seguintes solicitações, reclamações e demandas abertas pelos cidadãos através do aplicativo Colab:\\n\\n- **Assédio**\\n- **Levantamento de depósito**\\n- **Atendimento**\\n- **Reconhecimento de tempo de serviço / triênios**\\n- **Demora, grosseria ou falta de atendimento**\\n\\nPara reclamações de demora, grosseria, desvios ou falta de atendimento relacionados a estes assuntos, o cidadão também pode recorrer à Ouvidoria Geral do Município.",
  "metadata": {
    "category": "secretarias",
    "secretaria": "Secretaria Municipal de Administração",
    "demandas_count": 5
  }
}